{
  "name": "core",
  "files": [
    {
      "path": "/bin",
      "name": "busytex",
      "start": 0,
      "end": 1
    },
    {
      "path": "/etc/fonts",
      "name": "fonts.conf",
      "start": 1,
      "end": 180
    },
    {
      "path": "/etc",
      "name": "passwd",
      "start": 180,
      "end": 232
    },
    {
      "path": "/texlive",
      "name": "LICENSE.CTAN",
      "start": 232,
      "end": 2330
    },
    {
      "path": "/texlive",
      "name": "LICENSE.TL",
      "start": 2330,
      "end": 7597
    },
    {
      "path": "/texlive",
      "name": "README",
      "start": 7597,
      "end": 7779
    },
    {
      "path": "/texlive",
      "name": "README.usergroups",
      "start": 7779,
      "end": 8029
    },
    {
      "path": "/texlive",
      "name": "release-texlive.txt",
      "start": 8029,
      "end": 8379
    },
    {
      "path": "/texlive/tex/generic/tex-ini-files",
      "name": "dvilualatex.ini",
      "start": 8379,
      "end": 8463
    },
    {
      "path": "/texlive/tex/generic/tex-ini-files",
      "name": "dviluatex.ini",
      "start": 8463,
      "end": 8545
    },
    {
      "path": "/texlive/tex/generic/tex-ini-files",
      "name": "lualatex.ini",
      "start": 8545,
      "end": 9212
    },
    {
      "path": "/texlive/tex/generic/tex-ini-files",
      "name": "luatex.ini",
      "start": 9212,
      "end": 9501
    },
    {
      "path": "/texlive/tex/generic/tex-ini-files",
      "name": "luatexconfig.tex",
      "start": 9501,
      "end": 11537
    },
    {
      "path": "/texlive/tex/generic/tex-ini-files",
      "name": "pdftexconfig.tex",
      "start": 11537,
      "end": 12086
    },
    {
      "path": "/texlive/tex/generic/tex-ini-files",
      "name": "xelatex.ini",
      "start": 12086,
      "end": 12572
    },
    {
      "path": "/texlive/tex/generic/tex-ini-files",
      "name": "xetex.ini",
      "start": 12572,
      "end": 16000
    },
    {
      "path": "/texlive/tex/latex/latexconfig",
      "name": "epstopdf-sys.cfg",
      "start": 16000,
      "end": 16678
    },
    {
      "path": "/texlive/tex/latex/latexconfig",
      "name": "latex.ini",
      "start": 16678,
      "end": 17259
    },
    {
      "path": "/texlive/tex/latex/latexconfig",
      "name": "lualatexiniconfig.tex",
      "start": 17259,
      "end": 20844
    },
    {
      "path": "/texlive/tex/latex/latexconfig",
      "name": "lualatexquotejobname.lua",
      "start": 20844,
      "end": 21875
    },
    {
      "path": "/texlive/tex/latex/latexconfig",
      "name": "lualatexquotejobname.tex",
      "start": 21875,
      "end": 24321
    },
    {
      "path": "/texlive/tex/latex/latexconfig",
      "name": "mllatex.ini",
      "start": 24321,
      "end": 24387
    },
    {
      "path": "/texlive/tex/latex/latexconfig",
      "name": "pdflatex.ini",
      "start": 24387,
      "end": 24487
    },
    {
      "path": "/texlive/texmf-dist/fonts/enc/dvips/base",
      "name": "6w.enc",
      "start": 24487,
      "end": 29396
    },
    {
      "path": "/texlive/texmf-dist/fonts/enc/dvips/base",
      "name": "7t.enc",
      "start": 29396,
      "end": 32214
    },
    {
      "path": "/texlive/texmf-dist/fonts/enc/dvips/base",
      "name": "8a.enc",
      "start": 32214,
      "end": 34574
    },
    {
      "path": "/texlive/texmf-dist/fonts/enc/dvips/base",
      "name": "8r.enc",
      "start": 34574,
      "end": 39424
    },
    {
      "path": "/texlive/texmf-dist/fonts/enc/dvips/base",
      "name": "ad.enc",
      "start": 39424,
      "end": 42031
    },
    {
      "path": "/texlive/texmf-dist/fonts/enc/dvips/base",
      "name": "ansinew.enc",
      "start": 42031,
      "end": 46354
    },
    {
      "path": "/texlive/texmf-dist/fonts/enc/dvips/base",
      "name": "asex.enc",
      "start": 46354,
      "end": 52118
    },
    {
      "path": "/texlive/texmf-dist/fonts/enc/dvips/base",
      "name": "asexp.enc",
      "start": 52118,
      "end": 55908
    },
    {
      "path": "/texlive/texmf-dist/fonts/enc/dvips/base",
      "name": "dc.enc",
      "start": 55908,
      "end": 59309
    },
    {
      "path": "/texlive/texmf-dist/fonts/enc/dvips/base",
      "name": "dvips-all.enc",
      "start": 59309,
      "end": 242891
    },
    {
      "path": "/texlive/texmf-dist/fonts/enc/dvips/base",
      "name": "dvips.enc",
      "start": 242891,
      "end": 246560
    },
    {
      "path": "/texlive/texmf-dist/fonts/enc/dvips/base",
      "name": "ec.enc",
      "start": 246560,
      "end": 259202
    },
    {
      "path": "/texlive/texmf-dist/fonts/enc/dvips/base",
      "name": "extex.enc",
      "start": 259202,
      "end": 262572
    },
    {
      "path": "/texlive/texmf-dist/fonts/enc/dvips/base",
      "name": "funky.enc",
      "start": 262572,
      "end": 267428
    },
    {
      "path": "/texlive/texmf-dist/fonts/enc/dvips/base",
      "name": "odvips.enc",
      "start": 267428,
      "end": 270589
    },
    {
      "path": "/texlive/texmf-dist/fonts/enc/dvips/base",
      "name": "q-cs-uni.enc",
      "start": 270589,
      "end": 273138
    },
    {
      "path": "/texlive/texmf-dist/fonts/enc/dvips/base",
      "name": "q-ec-uni.enc",
      "start": 273138,
      "end": 275687
    },
    {
      "path": "/texlive/texmf-dist/fonts/enc/dvips/base",
      "name": "q-l7x-uni.enc",
      "start": 275687,
      "end": 278237
    },
    {
      "path": "/texlive/texmf-dist/fonts/enc/dvips/base",
      "name": "q-qx-uni.enc",
      "start": 278237,
      "end": 280782
    },
    {
      "path": "/texlive/texmf-dist/fonts/enc/dvips/base",
      "name": "q-rm-uni.enc",
      "start": 280782,
      "end": 283331
    },
    {
      "path": "/texlive/texmf-dist/fonts/enc/dvips/base",
      "name": "q-t2a-uni.enc",
      "start": 283331,
      "end": 285881
    },
    {
      "path": "/texlive/texmf-dist/fonts/enc/dvips/base",
      "name": "q-t2b-uni.enc",
      "start": 285881,
      "end": 288431
    },
    {
      "path": "/texlive/texmf-dist/fonts/enc/dvips/base",
      "name": "q-t2c-uni.enc",
      "start": 288431,
      "end": 290981
    },
    {
      "path": "/texlive/texmf-dist/fonts/enc/dvips/base",
      "name": "q-t5-uni.enc",
      "start": 290981,
      "end": 293530
    },
    {
      "path": "/texlive/texmf-dist/fonts/enc/dvips/base",
      "name": "q-texnansi-uni.enc",
      "start": 293530,
      "end": 296133
    },
    {
      "path": "/texlive/texmf-dist/fonts/enc/dvips/base",
      "name": "q-ts1-uni.enc",
      "start": 296133,
      "end": 298683
    },
    {
      "path": "/texlive/texmf-dist/fonts/enc/dvips/base",
      "name": "qx.enc",
      "start": 298683,
      "end": 300708
    },
    {
      "path": "/texlive/texmf-dist/fonts/enc/dvips/base",
      "name": "stormex.enc",
      "start": 300708,
      "end": 303117
    },
    {
      "path": "/texlive/texmf-dist/fonts/enc/dvips/base",
      "name": "tex256.enc",
      "start": 303117,
      "end": 307810
    },
    {
      "path": "/texlive/texmf-dist/fonts/enc/dvips/base",
      "name": "texmext.enc",
      "start": 307810,
      "end": 311636
    },
    {
      "path": "/texlive/texmf-dist/fonts/enc/dvips/base",
      "name": "texmital.enc",
      "start": 311636,
      "end": 314207
    },
    {
      "path": "/texlive/texmf-dist/fonts/enc/dvips/base",
      "name": "texmsym.enc",
      "start": 314207,
      "end": 317317
    },
    {
      "path": "/texlive/texmf-dist/fonts/enc/dvips/base",
      "name": "texnansx.enc",
      "start": 317317,
      "end": 322500
    },
    {
      "path": "/texlive/texmf-dist/fonts/enc/dvips/lm",
      "name": "lm-cs.enc",
      "start": 322500,
      "end": 324868
    },
    {
      "path": "/texlive/texmf-dist/fonts/enc/dvips/lm",
      "name": "lm-cssc.enc",
      "start": 324868,
      "end": 327266
    },
    {
      "path": "/texlive/texmf-dist/fonts/enc/dvips/lm",
      "name": "lm-cstt.enc",
      "start": 327266,
      "end": 329669
    },
    {
      "path": "/texlive/texmf-dist/fonts/enc/dvips/lm",
      "name": "lm-ec.enc",
      "start": 329669,
      "end": 332044
    },
    {
      "path": "/texlive/texmf-dist/fonts/enc/dvips/lm",
      "name": "lm-l7x.enc",
      "start": 332044,
      "end": 334497
    },
    {
      "path": "/texlive/texmf-dist/fonts/enc/dvips/lm",
      "name": "lm-mathex.enc",
      "start": 334497,
      "end": 337983
    },
    {
      "path": "/texlive/texmf-dist/fonts/enc/dvips/lm",
      "name": "lm-mathit.enc",
      "start": 337983,
      "end": 340388
    },
    {
      "path": "/texlive/texmf-dist/fonts/enc/dvips/lm",
      "name": "lm-mathsy.enc",
      "start": 340388,
      "end": 343228
    },
    {
      "path": "/texlive/texmf-dist/fonts/enc/dvips/lm",
      "name": "lm-qx.enc",
      "start": 343228,
      "end": 345609
    },
    {
      "path": "/texlive/texmf-dist/fonts/enc/dvips/lm",
      "name": "lm-qxsc.enc",
      "start": 345609,
      "end": 348021
    },
    {
      "path": "/texlive/texmf-dist/fonts/enc/dvips/lm",
      "name": "lm-qxtt.enc",
      "start": 348021,
      "end": 350429
    },
    {
      "path": "/texlive/texmf-dist/fonts/enc/dvips/lm",
      "name": "lm-rep-cmin.enc",
      "start": 350429,
      "end": 352922
    },
    {
      "path": "/texlive/texmf-dist/fonts/enc/dvips/lm",
      "name": "lm-rep-cmit.enc",
      "start": 352922,
      "end": 355223
    },
    {
      "path": "/texlive/texmf-dist/fonts/enc/dvips/lm",
      "name": "lm-rep-cmitt.enc",
      "start": 355223,
      "end": 357541
    },
    {
      "path": "/texlive/texmf-dist/fonts/enc/dvips/lm",
      "name": "lm-rep-cmrm.enc",
      "start": 357541,
      "end": 359840
    },
    {
      "path": "/texlive/texmf-dist/fonts/enc/dvips/lm",
      "name": "lm-rep-cmsc.enc",
      "start": 359840,
      "end": 362165
    },
    {
      "path": "/texlive/texmf-dist/fonts/enc/dvips/lm",
      "name": "lm-rep-cmtt.enc",
      "start": 362165,
      "end": 364480
    },
    {
      "path": "/texlive/texmf-dist/fonts/enc/dvips/lm",
      "name": "lm-rep-csin.enc",
      "start": 364480,
      "end": 366967
    },
    {
      "path": "/texlive/texmf-dist/fonts/enc/dvips/lm",
      "name": "lm-rep-csrm.enc",
      "start": 366967,
      "end": 369282
    },
    {
      "path": "/texlive/texmf-dist/fonts/enc/dvips/lm",
      "name": "lm-rep-cssc.enc",
      "start": 369282,
      "end": 371623
    },
    {
      "path": "/texlive/texmf-dist/fonts/enc/dvips/lm",
      "name": "lm-rep-cstt.enc",
      "start": 371623,
      "end": 373957
    },
    {
      "path": "/texlive/texmf-dist/fonts/enc/dvips/lm",
      "name": "lm-rep-plin.enc",
      "start": 373957,
      "end": 376449
    },
    {
      "path": "/texlive/texmf-dist/fonts/enc/dvips/lm",
      "name": "lm-rep-plit.enc",
      "start": 376449,
      "end": 378765
    },
    {
      "path": "/texlive/texmf-dist/fonts/enc/dvips/lm",
      "name": "lm-rep-plitt.enc",
      "start": 378765,
      "end": 381098
    },
    {
      "path": "/texlive/texmf-dist/fonts/enc/dvips/lm",
      "name": "lm-rep-plrm.enc",
      "start": 381098,
      "end": 383412
    },
    {
      "path": "/texlive/texmf-dist/fonts/enc/dvips/lm",
      "name": "lm-rep-plsc.enc",
      "start": 383412,
      "end": 385752
    },
    {
      "path": "/texlive/texmf-dist/fonts/enc/dvips/lm",
      "name": "lm-rep-pltt.enc",
      "start": 385752,
      "end": 388082
    },
    {
      "path": "/texlive/texmf-dist/fonts/enc/dvips/lm",
      "name": "lm-rep-t5psn.enc",
      "start": 388082,
      "end": 397189
    },
    {
      "path": "/texlive/texmf-dist/fonts/enc/dvips/lm",
      "name": "lm-rm.enc",
      "start": 397189,
      "end": 399516
    },
    {
      "path": "/texlive/texmf-dist/fonts/enc/dvips/lm",
      "name": "lm-rmsc.enc",
      "start": 399516,
      "end": 401871
    },
    {
      "path": "/texlive/texmf-dist/fonts/enc/dvips/lm",
      "name": "lm-rmtt.enc",
      "start": 401871,
      "end": 404230
    },
    {
      "path": "/texlive/texmf-dist/fonts/enc/dvips/lm",
      "name": "lm-t5.enc",
      "start": 404230,
      "end": 407132
    },
    {
      "path": "/texlive/texmf-dist/fonts/enc/dvips/lm",
      "name": "lm-texnansi.enc",
      "start": 407132,
      "end": 409611
    },
    {
      "path": "/texlive/texmf-dist/fonts/enc/dvips/lm",
      "name": "lm-ts1.enc",
      "start": 409611,
      "end": 412642
    },
    {
      "path": "/texlive/texmf-dist/fonts/enc/dvips/tetex",
      "name": "09fbbfac.enc",
      "start": 412642,
      "end": 414678
    },
    {
      "path": "/texlive/texmf-dist/fonts/enc/dvips/tetex",
      "name": "0ef0afca.enc",
      "start": 414678,
      "end": 416677
    },
    {
      "path": "/texlive/texmf-dist/fonts/enc/dvips/tetex",
      "name": "10037936.enc",
      "start": 416677,
      "end": 419333
    },
    {
      "path": "/texlive/texmf-dist/fonts/enc/dvips/tetex",
      "name": "1b6d048e.enc",
      "start": 419333,
      "end": 421551
    },
    {
      "path": "/texlive/texmf-dist/fonts/enc/dvips/tetex",
      "name": "71414f53.enc",
      "start": 421551,
      "end": 423566
    },
    {
      "path": "/texlive/texmf-dist/fonts/enc/dvips/tetex",
      "name": "74afc74c.enc",
      "start": 423566,
      "end": 425566
    },
    {
      "path": "/texlive/texmf-dist/fonts/enc/dvips/tetex",
      "name": "aae443f0.enc",
      "start": 425566,
      "end": 427598
    },
    {
      "path": "/texlive/texmf-dist/fonts/enc/dvips/tetex",
      "name": "b6a4d7c7.enc",
      "start": 427598,
      "end": 429611
    },
    {
      "path": "/texlive/texmf-dist/fonts/enc/dvips/tetex",
      "name": "bbad153f.enc",
      "start": 429611,
      "end": 432298
    },
    {
      "path": "/texlive/texmf-dist/fonts/enc/dvips/tetex",
      "name": "d9b29452.enc",
      "start": 432298,
      "end": 434493
    },
    {
      "path": "/texlive/texmf-dist/fonts/enc/dvips/tetex",
      "name": "f7b6d320.enc",
      "start": 434493,
      "end": 436683
    },
    {
      "path": "/texlive/texmf-dist/fonts/enc/dvips/tetex",
      "name": "mtex.enc",
      "start": 436683,
      "end": 440336
    },
    {
      "path": "/texlive/texmf-dist/fonts/map/dvipdfm/lm",
      "name": "lm-ec.map",
      "start": 440336,
      "end": 442380
    },
    {
      "path": "/texlive/texmf-dist/fonts/map/dvipdfm/lm",
      "name": "lm-math.map",
      "start": 442380,
      "end": 443200
    },
    {
      "path": "/texlive/texmf-dist/fonts/map/dvipdfm/lm",
      "name": "lm-rm.map",
      "start": 443200,
      "end": 445276
    },
    {
      "path": "/texlive/texmf-dist/fonts/map/dvipdfm/lm",
      "name": "lm-texnansi.map",
      "start": 445276,
      "end": 448184
    },
    {
      "path": "/texlive/texmf-dist/fonts/map/dvipdfmx",
      "name": "cid-x.map",
      "start": 448184,
      "end": 452620
    },
    {
      "path": "/texlive/texmf-dist/fonts/map/dvipdfmx",
      "name": "ckx.map",
      "start": 452620,
      "end": 453909
    },
    {
      "path": "/texlive/texmf-dist/fonts/map/dvips/amsfonts",
      "name": "cm.map",
      "start": 453909,
      "end": 456447
    },
    {
      "path": "/texlive/texmf-dist/fonts/map/dvips/amsfonts",
      "name": "cmextra.map",
      "start": 456447,
      "end": 457083
    },
    {
      "path": "/texlive/texmf-dist/fonts/map/dvips/amsfonts",
      "name": "cyrillic.map",
      "start": 457083,
      "end": 458043
    },
    {
      "path": "/texlive/texmf-dist/fonts/map/dvips/amsfonts",
      "name": "euler.map",
      "start": 458043,
      "end": 459658
    },
    {
      "path": "/texlive/texmf-dist/fonts/map/dvips/amsfonts",
      "name": "latxfont.map",
      "start": 459658,
      "end": 460446
    },
    {
      "path": "/texlive/texmf-dist/fonts/map/dvips/amsfonts",
      "name": "symbols.map",
      "start": 460446,
      "end": 461034
    },
    {
      "path": "/texlive/texmf-dist/fonts/map/dvips/cm",
      "name": "cmtext-bsr-interpolated.map",
      "start": 461034,
      "end": 461549
    },
    {
      "path": "/texlive/texmf-dist/fonts/map/dvips/dummy-space",
      "name": "dummy-space.map",
      "start": 461549,
      "end": 461879
    },
    {
      "path": "/texlive/texmf-dist/fonts/map/dvips/lm",
      "name": "lm-cs.map",
      "start": 461879,
      "end": 467728
    },
    {
      "path": "/texlive/texmf-dist/fonts/map/dvips/lm",
      "name": "lm-ec.map",
      "start": 467728,
      "end": 473513
    },
    {
      "path": "/texlive/texmf-dist/fonts/map/dvips/lm",
      "name": "lm-l7x.map",
      "start": 473513,
      "end": 479514
    },
    {
      "path": "/texlive/texmf-dist/fonts/map/dvips/lm",
      "name": "lm-math.map",
      "start": 479514,
      "end": 481683
    },
    {
      "path": "/texlive/texmf-dist/fonts/map/dvips/lm",
      "name": "lm-qx.map",
      "start": 481683,
      "end": 487532
    },
    {
      "path": "/texlive/texmf-dist/fonts/map/dvips/lm",
      "name": "lm-rep-cmother.map",
      "start": 487532,
      "end": 489854
    },
    {
      "path": "/texlive/texmf-dist/fonts/map/dvips/lm",
      "name": "lm-rep-cmtext-interpolated.map",
      "start": 489854,
      "end": 491293
    },
    {
      "path": "/texlive/texmf-dist/fonts/map/dvips/lm",
      "name": "lm-rep-cmtext.map",
      "start": 491293,
      "end": 497054
    },
    {
      "path": "/texlive/texmf-dist/fonts/map/dvips/lm",
      "name": "lm-rep-cstext.map",
      "start": 497054,
      "end": 502537
    },
    {
      "path": "/texlive/texmf-dist/fonts/map/dvips/lm",
      "name": "lm-rep-pltext.map",
      "start": 502537,
      "end": 508211
    },
    {
      "path": "/texlive/texmf-dist/fonts/map/dvips/lm",
      "name": "lm-rep-vntext.map",
      "start": 508211,
      "end": 513702
    },
    {
      "path": "/texlive/texmf-dist/fonts/map/dvips/lm",
      "name": "lm-rm.map",
      "start": 513702,
      "end": 519551
    },
    {
      "path": "/texlive/texmf-dist/fonts/map/dvips/lm",
      "name": "lm-t5.map",
      "start": 519551,
      "end": 525336
    },
    {
      "path": "/texlive/texmf-dist/fonts/map/dvips/lm",
      "name": "lm-texnansi.map",
      "start": 525336,
      "end": 532417
    },
    {
      "path": "/texlive/texmf-dist/fonts/map/dvips/lm",
      "name": "lm-ts1.map",
      "start": 532417,
      "end": 538418
    },
    {
      "path": "/texlive/texmf-dist/fonts/map/dvips/lm",
      "name": "lm.map",
      "start": 538418,
      "end": 586090
    },
    {
      "path": "/texlive/texmf-dist/fonts/map/dvips/pslatex",
      "name": "pcrr8rn.map",
      "start": 586090,
      "end": 586268
    },
    {
      "path": "/texlive/texmf-dist/fonts/map/dvips/psnfss",
      "name": "charter.map",
      "start": 586268,
      "end": 586771
    },
    {
      "path": "/texlive/texmf-dist/fonts/map/dvips/psnfss",
      "name": "fpls.map",
      "start": 586771,
      "end": 587111
    },
    {
      "path": "/texlive/texmf-dist/fonts/map/dvips/psnfss",
      "name": "pazo.map",
      "start": 587111,
      "end": 587285
    },
    {
      "path": "/texlive/texmf-dist/fonts/map/dvips/psnfss",
      "name": "psnfss.map",
      "start": 587285,
      "end": 590344
    },
    {
      "path": "/texlive/texmf-dist/fonts/map/dvips/psnfss",
      "name": "utopia.map",
      "start": 590344,
      "end": 590833
    },
    {
      "path": "/texlive/texmf-dist/fonts/map/dvips/rsfs",
      "name": "rsfs.map",
      "start": 590833,
      "end": 590942
    },
    {
      "path": "/texlive/texmf-dist/fonts/map/dvips/symbol",
      "name": "usy.map",
      "start": 590942,
      "end": 590970
    },
    {
      "path": "/texlive/texmf-dist/fonts/map/dvips/tetex",
      "name": "Makefile",
      "start": 590970,
      "end": 592519
    },
    {
      "path": "/texlive/texmf-dist/fonts/map/dvips/tetex",
      "name": "README",
      "start": 592519,
      "end": 594715
    },
    {
      "path": "/texlive/texmf-dist/fonts/map/dvips/tetex",
      "name": "base14flags.ltx",
      "start": 594715,
      "end": 595072
    },
    {
      "path": "/texlive/texmf-dist/fonts/map/dvips/tetex",
      "name": "base14flags.tex",
      "start": 595072,
      "end": 596507
    },
    {
      "path": "/texlive/texmf-dist/fonts/map/dvips/tetex",
      "name": "dvipdfm35.map",
      "start": 596507,
      "end": 615539
    },
    {
      "path": "/texlive/texmf-dist/fonts/map/dvips/tetex",
      "name": "dvips35.map",
      "start": 615539,
      "end": 631684
    },
    {
      "path": "/texlive/texmf-dist/fonts/map/dvips/tetex",
      "name": "mathpple.map",
      "start": 631684,
      "end": 631961
    },
    {
      "path": "/texlive/texmf-dist/fonts/map/dvips/tetex",
      "name": "pdftex35.map",
      "start": 631961,
      "end": 652265
    },
    {
      "path": "/texlive/texmf-dist/fonts/map/dvips/tetex",
      "name": "ps2pk35.map",
      "start": 652265,
      "end": 673410
    },
    {
      "path": "/texlive/texmf-dist/fonts/map/dvips/zapfding",
      "name": "uzd.map",
      "start": 673410,
      "end": 673434
    },
    {
      "path": "/texlive/texmf-dist/fonts/map/glyphlist",
      "name": "glyphlist.txt",
      "start": 673434,
      "end": 750580
    },
    {
      "path": "/texlive/texmf-dist/fonts/map/glyphlist",
      "name": "pdfglyphlist.txt",
      "start": 750580,
      "end": 755697
    },
    {
      "path": "/texlive/texmf-dist/fonts/map/glyphlist",
      "name": "texglyphlist.txt",
      "start": 755697,
      "end": 765924
    },
    {
      "path": "/texlive/texmf-dist/fonts/tfm/public/cm",
      "name": "cmb10.tfm",
      "start": 765924,
      "end": 767260
    },
    {
      "path": "/texlive/texmf-dist/fonts/tfm/public/cm",
      "name": "cmbsy10.tfm",
      "start": 767260,
      "end": 768376
    },
    {
      "path": "/texlive/texmf-dist/fonts/tfm/public/cm",
      "name": "cmbx10.tfm",
      "start": 768376,
      "end": 769704
    },
    {
      "path": "/texlive/texmf-dist/fonts/tfm/public/cm",
      "name": "cmbx12.tfm",
      "start": 769704,
      "end": 771028
    },
    {
      "path": "/texlive/texmf-dist/fonts/tfm/public/cm",
      "name": "cmbx5.tfm",
      "start": 771028,
      "end": 772360
    },
    {
      "path": "/texlive/texmf-dist/fonts/tfm/public/cm",
      "name": "cmbx6.tfm",
      "start": 772360,
      "end": 773704
    },
    {
      "path": "/texlive/texmf-dist/fonts/tfm/public/cm",
      "name": "cmbx7.tfm",
      "start": 773704,
      "end": 775040
    },
    {
      "path": "/texlive/texmf-dist/fonts/tfm/public/cm",
      "name": "cmbx8.tfm",
      "start": 775040,
      "end": 776372
    },
    {
      "path": "/texlive/texmf-dist/fonts/tfm/public/cm",
      "name": "cmbx9.tfm",
      "start": 776372,
      "end": 777700
    },
    {
      "path": "/texlive/texmf-dist/fonts/tfm/public/cm",
      "name": "cmbxsl10.tfm",
      "start": 777700,
      "end": 779232
    },
    {
      "path": "/texlive/texmf-dist/fonts/tfm/public/cm",
      "name": "cmbxti10.tfm",
      "start": 779232,
      "end": 780764
    },
    {
      "path": "/texlive/texmf-dist/fonts/tfm/public/cm",
      "name": "cmcsc10.tfm",
      "start": 780764,
      "end": 782064
    },
    {
      "path": "/texlive/texmf-dist/fonts/tfm/public/cm",
      "name": "cmdunh10.tfm",
      "start": 782064,
      "end": 783360
    },
    {
      "path": "/texlive/texmf-dist/fonts/tfm/public/cm",
      "name": "cmex10.tfm",
      "start": 783360,
      "end": 784352
    },
    {
      "path": "/texlive/texmf-dist/fonts/tfm/public/cm",
      "name": "cmff10.tfm",
      "start": 784352,
      "end": 785676
    },
    {
      "path": "/texlive/texmf-dist/fonts/tfm/public/cm",
      "name": "cmfi10.tfm",
      "start": 785676,
      "end": 787100
    },
    {
      "path": "/texlive/texmf-dist/fonts/tfm/public/cm",
      "name": "cmfib8.tfm",
      "start": 787100,
      "end": 788380
    },
    {
      "path": "/texlive/texmf-dist/fonts/tfm/public/cm",
      "name": "cminch.tfm",
      "start": 788380,
      "end": 788872
    },
    {
      "path": "/texlive/texmf-dist/fonts/tfm/public/cm",
      "name": "cmitt10.tfm",
      "start": 788872,
      "end": 789640
    },
    {
      "path": "/texlive/texmf-dist/fonts/tfm/public/cm",
      "name": "cmmi10.tfm",
      "start": 789640,
      "end": 791168
    },
    {
      "path": "/texlive/texmf-dist/fonts/tfm/public/cm",
      "name": "cmmi12.tfm",
      "start": 791168,
      "end": 792692
    },
    {
      "path": "/texlive/texmf-dist/fonts/tfm/public/cm",
      "name": "cmmi5.tfm",
      "start": 792692,
      "end": 794200
    },
    {
      "path": "/texlive/texmf-dist/fonts/tfm/public/cm",
      "name": "cmmi6.tfm",
      "start": 794200,
      "end": 795712
    },
    {
      "path": "/texlive/texmf-dist/fonts/tfm/public/cm",
      "name": "cmmi7.tfm",
      "start": 795712,
      "end": 797240
    },
    {
      "path": "/texlive/texmf-dist/fonts/tfm/public/cm",
      "name": "cmmi8.tfm",
      "start": 797240,
      "end": 798760
    },
    {
      "path": "/texlive/texmf-dist/fonts/tfm/public/cm",
      "name": "cmmi9.tfm",
      "start": 798760,
      "end": 800284
    },
    {
      "path": "/texlive/texmf-dist/fonts/tfm/public/cm",
      "name": "cmmib10.tfm",
      "start": 800284,
      "end": 801808
    },
    {
      "path": "/texlive/texmf-dist/fonts/tfm/public/cm",
      "name": "cmr10.tfm",
      "start": 801808,
      "end": 803104
    },
    {
      "path": "/texlive/texmf-dist/fonts/tfm/public/cm",
      "name": "cmr12.tfm",
      "start": 803104,
      "end": 804392
    },
    {
      "path": "/texlive/texmf-dist/fonts/tfm/public/cm",
      "name": "cmr17.tfm",
      "start": 804392,
      "end": 805684
    },
    {
      "path": "/texlive/texmf-dist/fonts/tfm/public/cm",
      "name": "cmr5.tfm",
      "start": 805684,
      "end": 806904
    },
    {
      "path": "/texlive/texmf-dist/fonts/tfm/public/cm",
      "name": "cmr6.tfm",
      "start": 806904,
      "end": 808204
    },
    {
      "path": "/texlive/texmf-dist/fonts/tfm/public/cm",
      "name": "cmr7.tfm",
      "start": 808204,
      "end": 809504
    },
    {
      "path": "/texlive/texmf-dist/fonts/tfm/public/cm",
      "name": "cmr8.tfm",
      "start": 809504,
      "end": 810796
    },
    {
      "path": "/texlive/texmf-dist/fonts/tfm/public/cm",
      "name": "cmr9.tfm",
      "start": 810796,
      "end": 812088
    },
    {
      "path": "/texlive/texmf-dist/fonts/tfm/public/cm",
      "name": "cmsl10.tfm",
      "start": 812088,
      "end": 813596
    },
    {
      "path": "/texlive/texmf-dist/fonts/tfm/public/cm",
      "name": "cmsl12.tfm",
      "start": 813596,
      "end": 815100
    },
    {
      "path": "/texlive/texmf-dist/fonts/tfm/public/cm",
      "name": "cmsl8.tfm",
      "start": 815100,
      "end": 816604
    },
    {
      "path": "/texlive/texmf-dist/fonts/tfm/public/cm",
      "name": "cmsl9.tfm",
      "start": 816604,
      "end": 818108
    },
    {
      "path": "/texlive/texmf-dist/fonts/tfm/public/cm",
      "name": "cmsltt10.tfm",
      "start": 818108,
      "end": 818880
    },
    {
      "path": "/texlive/texmf-dist/fonts/tfm/public/cm",
      "name": "cmss10.tfm",
      "start": 818880,
      "end": 820196
    },
    {
      "path": "/texlive/texmf-dist/fonts/tfm/public/cm",
      "name": "cmss12.tfm",
      "start": 820196,
      "end": 821520
    },
    {
      "path": "/texlive/texmf-dist/fonts/tfm/public/cm",
      "name": "cmss17.tfm",
      "start": 821520,
      "end": 822840
    },
    {
      "path": "/texlive/texmf-dist/fonts/tfm/public/cm",
      "name": "cmss8.tfm",
      "start": 822840,
      "end": 824136
    },
    {
      "path": "/texlive/texmf-dist/fonts/tfm/public/cm",
      "name": "cmss9.tfm",
      "start": 824136,
      "end": 825456
    },
    {
      "path": "/texlive/texmf-dist/fonts/tfm/public/cm",
      "name": "cmssbx10.tfm",
      "start": 825456,
      "end": 826728
    },
    {
      "path": "/texlive/texmf-dist/fonts/tfm/public/cm",
      "name": "cmssdc10.tfm",
      "start": 826728,
      "end": 828056
    },
    {
      "path": "/texlive/texmf-dist/fonts/tfm/public/cm",
      "name": "cmssi10.tfm",
      "start": 828056,
      "end": 829576
    },
    {
      "path": "/texlive/texmf-dist/fonts/tfm/public/cm",
      "name": "cmssi12.tfm",
      "start": 829576,
      "end": 831108
    },
    {
      "path": "/texlive/texmf-dist/fonts/tfm/public/cm",
      "name": "cmssi17.tfm",
      "start": 831108,
      "end": 832636
    },
    {
      "path": "/texlive/texmf-dist/fonts/tfm/public/cm",
      "name": "cmssi8.tfm",
      "start": 832636,
      "end": 834136
    },
    {
      "path": "/texlive/texmf-dist/fonts/tfm/public/cm",
      "name": "cmssi9.tfm",
      "start": 834136,
      "end": 835660
    },
    {
      "path": "/texlive/texmf-dist/fonts/tfm/public/cm",
      "name": "cmssq8.tfm",
      "start": 835660,
      "end": 836964
    },
    {
      "path": "/texlive/texmf-dist/fonts/tfm/public/cm",
      "name": "cmssqi8.tfm",
      "start": 836964,
      "end": 838460
    },
    {
      "path": "/texlive/texmf-dist/fonts/tfm/public/cm",
      "name": "cmsy10.tfm",
      "start": 838460,
      "end": 839584
    },
    {
      "path": "/texlive/texmf-dist/fonts/tfm/public/cm",
      "name": "cmsy5.tfm",
      "start": 839584,
      "end": 840696
    },
    {
      "path": "/texlive/texmf-dist/fonts/tfm/public/cm",
      "name": "cmsy6.tfm",
      "start": 840696,
      "end": 841812
    },
    {
      "path": "/texlive/texmf-dist/fonts/tfm/public/cm",
      "name": "cmsy7.tfm",
      "start": 841812,
      "end": 842932
    },
    {
      "path": "/texlive/texmf-dist/fonts/tfm/public/cm",
      "name": "cmsy8.tfm",
      "start": 842932,
      "end": 844052
    },
    {
      "path": "/texlive/texmf-dist/fonts/tfm/public/cm",
      "name": "cmsy9.tfm",
      "start": 844052,
      "end": 845168
    },
    {
      "path": "/texlive/texmf-dist/fonts/tfm/public/cm",
      "name": "cmtcsc10.tfm",
      "start": 845168,
      "end": 845944
    },
    {
      "path": "/texlive/texmf-dist/fonts/tfm/public/cm",
      "name": "cmtex10.tfm",
      "start": 845944,
      "end": 846712
    },
    {
      "path": "/texlive/texmf-dist/fonts/tfm/public/cm",
      "name": "cmtex8.tfm",
      "start": 846712,
      "end": 847480
    },
    {
      "path": "/texlive/texmf-dist/fonts/tfm/public/cm",
      "name": "cmtex9.tfm",
      "start": 847480,
      "end": 848244
    },
    {
      "path": "/texlive/texmf-dist/fonts/tfm/public/cm",
      "name": "cmti10.tfm",
      "start": 848244,
      "end": 849724
    },
    {
      "path": "/texlive/texmf-dist/fonts/tfm/public/cm",
      "name": "cmti12.tfm",
      "start": 849724,
      "end": 851208
    },
    {
      "path": "/texlive/texmf-dist/fonts/tfm/public/cm",
      "name": "cmti7.tfm",
      "start": 851208,
      "end": 852700
    },
    {
      "path": "/texlive/texmf-dist/fonts/tfm/public/cm",
      "name": "cmti8.tfm",
      "start": 852700,
      "end": 854204
    },
    {
      "path": "/texlive/texmf-dist/fonts/tfm/public/cm",
      "name": "cmti9.tfm",
      "start": 854204,
      "end": 855680
    },
    {
      "path": "/texlive/texmf-dist/fonts/tfm/public/cm",
      "name": "cmtt10.tfm",
      "start": 855680,
      "end": 856448
    },
    {
      "path": "/texlive/texmf-dist/fonts/tfm/public/cm",
      "name": "cmtt12.tfm",
      "start": 856448,
      "end": 857220
    },
    {
      "path": "/texlive/texmf-dist/fonts/tfm/public/cm",
      "name": "cmtt8.tfm",
      "start": 857220,
      "end": 857988
    },
    {
      "path": "/texlive/texmf-dist/fonts/tfm/public/cm",
      "name": "cmtt9.tfm",
      "start": 857988,
      "end": 858752
    },
    {
      "path": "/texlive/texmf-dist/fonts/tfm/public/cm",
      "name": "cmu10.tfm",
      "start": 858752,
      "end": 860028
    },
    {
      "path": "/texlive/texmf-dist/fonts/tfm/public/cm",
      "name": "cmvtt10.tfm",
      "start": 860028,
      "end": 861276
    },
    {
      "path": "/texlive/texmf-dist",
      "name": "ls-R",
      "start": 861276,
      "end": 1027851
    },
    {
      "path": "/texlive/texmf-dist/tex/generic/iftex",
      "name": "ifetex.sty",
      "start": 1027851,
      "end": 1028380
    },
    {
      "path": "/texlive/texmf-dist/tex/generic/iftex",
      "name": "ifluatex.sty",
      "start": 1028380,
      "end": 1028872
    },
    {
      "path": "/texlive/texmf-dist/tex/generic/iftex",
      "name": "ifpdf.sty",
      "start": 1028872,
      "end": 1029352
    },
    {
      "path": "/texlive/texmf-dist/tex/generic/iftex",
      "name": "iftex.sty",
      "start": 1029352,
      "end": 1036589
    },
    {
      "path": "/texlive/texmf-dist/tex/generic/iftex",
      "name": "ifvtex.sty",
      "start": 1036589,
      "end": 1037646
    },
    {
      "path": "/texlive/texmf-dist/tex/generic/iftex",
      "name": "ifxetex.sty",
      "start": 1037646,
      "end": 1038134
    },
    {
      "path": "/texlive/texmf-dist/tex/latex/base",
      "name": "alltt.sty",
      "start": 1038134,
      "end": 1041271
    },
    {
      "path": "/texlive/texmf-dist/tex/latex/base",
      "name": "ansinew.def",
      "start": 1041271,
      "end": 1048100
    },
    {
      "path": "/texlive/texmf-dist/tex/latex/base",
      "name": "applemac.def",
      "start": 1048100,
      "end": 1054504
    },
    {
      "path": "/texlive/texmf-dist/tex/latex/base",
      "name": "article.cls",
      "start": 1054504,
      "end": 1074648
    },
    {
      "path": "/texlive/texmf-dist/tex/latex/base",
      "name": "article.sty",
      "start": 1074648,
      "end": 1076388
    },
    {
      "path": "/texlive/texmf-dist/tex/latex/base",
      "name": "ascii.def",
      "start": 1076388,
      "end": 1078119
    },
    {
      "path": "/texlive/texmf-dist/tex/latex/base",
      "name": "atbegshi-ltx.sty",
      "start": 1078119,
      "end": 1081082
    },
    {
      "path": "/texlive/texmf-dist/tex/latex/base",
      "name": "atveryend-ltx.sty",
      "start": 1081082,
      "end": 1083460
    },
    {
      "path": "/texlive/texmf-dist/tex/latex/base",
      "name": "bezier.sty",
      "start": 1083460,
      "end": 1085520
    },
    {
      "path": "/texlive/texmf-dist/tex/latex/base",
      "name": "bk10.clo",
      "start": 1085520,
      "end": 1093808
    },
    {
      "path": "/texlive/texmf-dist/tex/latex/base",
      "name": "bk11.clo",
      "start": 1093808,
      "end": 1102111
    },
    {
      "path": "/texlive/texmf-dist/tex/latex/base",
      "name": "bk12.clo",
      "start": 1102111,
      "end": 1110396
    },
    {
      "path": "/texlive/texmf-dist/tex/latex/base",
      "name": "book.cls",
      "start": 1110396,
      "end": 1133664
    },
    {
      "path": "/texlive/texmf-dist/tex/latex/base",
      "name": "book.sty",
      "start": 1133664,
      "end": 1135386
    },
    {
      "path": "/texlive/texmf-dist/tex/latex/base",
      "name": "cp1250.def",
      "start": 1135386,
      "end": 1141622
    },
    {
      "path": "/texlive/texmf-dist/tex/latex/base",
      "name": "cp1252.def",
      "start": 1141622,
      "end": 1148440
    },
    {
      "path": "/texlive/texmf-dist/tex/latex/base",
      "name": "cp1257.def",
      "start": 1148440,
      "end": 1154889
    },
    {
      "path": "/texlive/texmf-dist/tex/latex/base",
      "name": "cp437.def",
      "start": 1154889,
      "end": 1159686
    },
    {
      "path": "/texlive/texmf-dist/tex/latex/base",
      "name": "cp437de.def",
      "start": 1159686,
      "end": 1164489
    },
    {
      "path": "/texlive/texmf-dist/tex/latex/base",
      "name": "cp850.def",
      "start": 1164489,
      "end": 1170545
    },
    {
      "path": "/texlive/texmf-dist/tex/latex/base",
      "name": "cp852.def",
      "start": 1170545,
      "end": 1176054
    },
    {
      "path": "/texlive/texmf-dist/tex/latex/base",
      "name": "cp858.def",
      "start": 1176054,
      "end": 1182062
    },
    {
      "path": "/texlive/texmf-dist/tex/latex/base",
      "name": "cp865.def",
      "start": 1182062,
      "end": 1186927
    },
    {
      "path": "/texlive/texmf-dist/tex/latex/base",
      "name": "decmulti.def",
      "start": 1186927,
      "end": 1191927
    },
    {
      "path": "/texlive/texmf-dist/tex/latex/base",
      "name": "doc-2016-02-15.sty",
      "start": 1191927,
      "end": 1221892
    },
    {
      "path": "/texlive/texmf-dist/tex/latex/base",
      "name": "doc-2021-06-01.sty",
      "start": 1221892,
      "end": 1252391
    },
    {
      "path": "/texlive/texmf-dist/tex/latex/base",
      "name": "doc.sty",
      "start": 1252391,
      "end": 1295377
    },
    {
      "path": "/texlive/texmf-dist/tex/latex/base",
      "name": "docstrip.tex",
      "start": 1295377,
      "end": 1330158
    },
    {
      "path": "/texlive/texmf-dist/tex/latex/base",
      "name": "exscale.sty",
      "start": 1330158,
      "end": 1332739
    },
    {
      "path": "/texlive/texmf-dist/tex/latex/base",
      "name": "fix-cm.sty",
      "start": 1332739,
      "end": 1347480
    },
    {
      "path": "/texlive/texmf-dist/tex/latex/base",
      "name": "fixltx2e.sty",
      "start": 1347480,
      "end": 1362989
    },
    {
      "path": "/texlive/texmf-dist/tex/latex/base",
      "name": "flafter.sty",
      "start": 1362989,
      "end": 1372818
    },
    {
      "path": "/texlive/texmf-dist/tex/latex/base",
      "name": "fleqn.clo",
      "start": 1372818,
      "end": 1377625
    },
    {
      "path": "/texlive/texmf-dist/tex/latex/base",
      "name": "fleqn.sty",
      "start": 1377625,
      "end": 1379328
    },
    {
      "path": "/texlive/texmf-dist/tex/latex/base",
      "name": "fltrace.sty",
      "start": 1379328,
      "end": 1418579
    },
    {
      "path": "/texlive/texmf-dist/tex/latex/base",
      "name": "fontenc.sty",
      "start": 1418579,
      "end": 1423854
    },
    {
      "path": "/texlive/texmf-dist/tex/latex/base",
      "name": "fontmath.cfg",
      "start": 1423854,
      "end": 1425832
    },
    {
      "path": "/texlive/texmf-dist/tex/latex/base",
      "name": "fontmath.ltx",
      "start": 1425832,
      "end": 1450776
    },
    {
      "path": "/texlive/texmf-dist/tex/latex/base",
      "name": "fonttext.cfg",
      "start": 1450776,
      "end": 1452754
    },
    {
      "path": "/texlive/texmf-dist/tex/latex/base",
      "name": "fonttext.ltx",
      "start": 1452754,
      "end": 1456071
    },
    {
      "path": "/texlive/texmf-dist/tex/latex/base",
      "name": "graphpap.sty",
      "start": 1456071,
      "end": 1459461
    },
    {
      "path": "/texlive/texmf-dist/tex/latex/base",
      "name": "hyphen.ltx",
      "start": 1459461,
      "end": 1461399
    },
    {
      "path": "/texlive/texmf-dist/tex/latex/base",
      "name": "idx.tex",
      "start": 1461399,
      "end": 1464104
    },
    {
      "path": "/texlive/texmf-dist/tex/latex/base",
      "name": "ifthen.sty",
      "start": 1464104,
      "end": 1469629
    },
    {
      "path": "/texlive/texmf-dist/tex/latex/base",
      "name": "inputenc.sty",
      "start": 1469629,
      "end": 1474677
    },
    {
      "path": "/texlive/texmf-dist/tex/latex/base",
      "name": "lablst.tex",
      "start": 1474677,
      "end": 1478756
    },
    {
      "path": "/texlive/texmf-dist/tex/latex/base",
      "name": "latex.ltx",
      "start": 1478756,
      "end": 2156774
    },
    {
      "path": "/texlive/texmf-dist/tex/latex/base",
      "name": "latex209.def",
      "start": 2156774,
      "end": 2169123
    },
    {
      "path": "/texlive/texmf-dist/tex/latex/base",
      "name": "latexrelease.sty",
      "start": 2169123,
      "end": 2890664
    },
    {
      "path": "/texlive/texmf-dist/tex/latex/base",
      "name": "latexsym.sty",
      "start": 2890664,
      "end": 2893517
    },
    {
      "path": "/texlive/texmf-dist/tex/latex/base",
      "name": "latin1.def",
      "start": 2893517,
      "end": 2899192
    },
    {
      "path": "/texlive/texmf-dist/tex/latex/base",
      "name": "latin10.def",
      "start": 2899192,
      "end": 2904583
    },
    {
      "path": "/texlive/texmf-dist/tex/latex/base",
      "name": "latin2.def",
      "start": 2904583,
      "end": 2909537
    },
    {
      "path": "/texlive/texmf-dist/tex/latex/base",
      "name": "latin3.def",
      "start": 2909537,
      "end": 2914604
    },
    {
      "path": "/texlive/texmf-dist/tex/latex/base",
      "name": "latin4.def",
      "start": 2914604,
      "end": 2919795
    },
    {
      "path": "/texlive/texmf-dist/tex/latex/base",
      "name": "latin5.def",
      "start": 2919795,
      "end": 2925447
    },
    {
      "path": "/texlive/texmf-dist/tex/latex/base",
      "name": "latin9.def",
      "start": 2925447,
      "end": 2930768
    },
    {
      "path": "/texlive/texmf-dist/tex/latex/base",
      "name": "lcyenc.dfu",
      "start": 2930768,
      "end": 2937964
    },
    {
      "path": "/texlive/texmf-dist/tex/latex/base",
      "name": "leqno.clo",
      "start": 2937964,
      "end": 2939922
    },
    {
      "path": "/texlive/texmf-dist/tex/latex/base",
      "name": "leqno.sty",
      "start": 2939922,
      "end": 2941625
    },
    {
      "path": "/texlive/texmf-dist/tex/latex/base",
      "name": "letter.cls",
      "start": 2941625,
      "end": 2955353
    },
    {
      "path": "/texlive/texmf-dist/tex/latex/base",
      "name": "letter.sty",
      "start": 2955353,
      "end": 2957087
    },
    {
      "path": "/texlive/texmf-dist/tex/latex/base",
      "name": "lppl.tex",
      "start": 2957087,
      "end": 2980473
    },
    {
      "path": "/texlive/texmf-dist/tex/latex/base",
      "name": "ltluatex.lua",
      "start": 2980473,
      "end": 3005068
    },
    {
      "path": "/texlive/texmf-dist/tex/latex/base",
      "name": "ltluatex.tex",
      "start": 3005068,
      "end": 3013871
    },
    {
      "path": "/texlive/texmf-dist/tex/latex/base",
      "name": "ltnews.cls",
      "start": 3013871,
      "end": 3035359
    },
    {
      "path": "/texlive/texmf-dist/tex/latex/base",
      "name": "ltxcheck.tex",
      "start": 3035359,
      "end": 3062481
    },
    {
      "path": "/texlive/texmf-dist/tex/latex/base",
      "name": "ltxdoc.cfg",
      "start": 3062481,
      "end": 3064715
    },
    {
      "path": "/texlive/texmf-dist/tex/latex/base",
      "name": "ltxdoc.cls",
      "start": 3064715,
      "end": 3073428
    },
    {
      "path": "/texlive/texmf-dist/tex/latex/base",
      "name": "ltxguide.cls",
      "start": 3073428,
      "end": 3080956
    },
    {
      "path": "/texlive/texmf-dist/tex/latex/base",
      "name": "ly1enc.dfu",
      "start": 3080956,
      "end": 3087993
    },
    {
      "path": "/texlive/texmf-dist/tex/latex/base",
      "name": "macce.def",
      "start": 3087993,
      "end": 3091759
    },
    {
      "path": "/texlive/texmf-dist/tex/latex/base",
      "name": "makeidx.sty",
      "start": 3091759,
      "end": 3093698
    },
    {
      "path": "/texlive/texmf-dist/tex/latex/base",
      "name": "minimal.cls",
      "start": 3093698,
      "end": 3095639
    },
    {
      "path": "/texlive/texmf-dist/tex/latex/base",
      "name": "newlfont.sty",
      "start": 3095639,
      "end": 3098550
    },
    {
      "path": "/texlive/texmf-dist/tex/latex/base",
      "name": "next.def",
      "start": 3098550,
      "end": 3105258
    },
    {
      "path": "/texlive/texmf-dist/tex/latex/base",
      "name": "nfssfont.tex",
      "start": 3105258,
      "end": 3118578
    },
    {
      "path": "/texlive/texmf-dist/tex/latex/base",
      "name": "oldlfont.sty",
      "start": 3118578,
      "end": 3122028
    },
    {
      "path": "/texlive/texmf-dist/tex/latex/base",
      "name": "omlcmm.fd",
      "start": 3122028,
      "end": 3124360
    },
    {
      "path": "/texlive/texmf-dist/tex/latex/base",
      "name": "omlcmr.fd",
      "start": 3124360,
      "end": 3126830
    },
    {
      "path": "/texlive/texmf-dist/tex/latex/base",
      "name": "omlenc.def",
      "start": 3126830,
      "end": 3128777
    },
    {
      "path": "/texlive/texmf-dist/tex/latex/base",
      "name": "omllcmm.fd",
      "start": 3128777,
      "end": 3131019
    },
    {
      "path": "/texlive/texmf-dist/tex/latex/base",
      "name": "omscmr.fd",
      "start": 3131019,
      "end": 3133488
    },
    {
      "path": "/texlive/texmf-dist/tex/latex/base",
      "name": "omscmsy.fd",
      "start": 3133488,
      "end": 3135750
    },
    {
      "path": "/texlive/texmf-dist/tex/latex/base",
      "name": "omsenc.def",
      "start": 3135750,
      "end": 3138489
    },
    {
      "path": "/texlive/texmf-dist/tex/latex/base",
      "name": "omsenc.dfu",
      "start": 3138489,
      "end": 3140479
    },
    {
      "path": "/texlive/texmf-dist/tex/latex/base",
      "name": "omslcmsy.fd",
      "start": 3140479,
      "end": 3142725
    },
    {
      "path": "/texlive/texmf-dist/tex/latex/base",
      "name": "omxcmex.fd",
      "start": 3142725,
      "end": 3144765
    },
    {
      "path": "/texlive/texmf-dist/tex/latex/base",
      "name": "omxlcmex.fd",
      "start": 3144765,
      "end": 3146914
    },
    {
      "path": "/texlive/texmf-dist/tex/latex/base",
      "name": "openbib.sty",
      "start": 3146914,
      "end": 3148835
    },
    {
      "path": "/texlive/texmf-dist/tex/latex/base",
      "name": "ot1cmdh.fd",
      "start": 3148835,
      "end": 3150894
    },
    {
      "path": "/texlive/texmf-dist/tex/latex/base",
      "name": "ot1cmfib.fd",
      "start": 3150894,
      "end": 3152956
    },
    {
      "path": "/texlive/texmf-dist/tex/latex/base",
      "name": "ot1cmfr.fd",
      "start": 3152956,
      "end": 3155077
    },
    {
      "path": "/texlive/texmf-dist/tex/latex/base",
      "name": "ot1cmr.fd",
      "start": 3155077,
      "end": 3158782
    },
    {
      "path": "/texlive/texmf-dist/tex/latex/base",
      "name": "ot1cmss.fd",
      "start": 3158782,
      "end": 3161934
    },
    {
      "path": "/texlive/texmf-dist/tex/latex/base",
      "name": "ot1cmtt.fd",
      "start": 3161934,
      "end": 3164843
    },
    {
      "path": "/texlive/texmf-dist/tex/latex/base",
      "name": "ot1cmvtt.fd",
      "start": 3164843,
      "end": 3167114
    },
    {
      "path": "/texlive/texmf-dist/tex/latex/base",
      "name": "ot1enc.def",
      "start": 3167114,
      "end": 3171807
    },
    {
      "path": "/texlive/texmf-dist/tex/latex/base",
      "name": "ot1enc.dfu",
      "start": 3171807,
      "end": 3175341
    },
    {
      "path": "/texlive/texmf-dist/tex/latex/base",
      "name": "ot1lcmss.fd",
      "start": 3175341,
      "end": 3178338
    },
    {
      "path": "/texlive/texmf-dist/tex/latex/base",
      "name": "ot1lcmtt.fd",
      "start": 3178338,
      "end": 3180825
    },
    {
      "path": "/texlive/texmf-dist/tex/latex/base",
      "name": "ot2enc.dfu",
      "start": 3180825,
      "end": 3188241
    },
    {
      "path": "/texlive/texmf-dist/tex/latex/base",
      "name": "ot4enc.def",
      "start": 3188241,
      "end": 3193023
    },
    {
      "path": "/texlive/texmf-dist/tex/latex/base",
      "name": "preload.cfg",
      "start": 3193023,
      "end": 3195000
    },
    {
      "path": "/texlive/texmf-dist/tex/latex/base",
      "name": "preload.ltx",
      "start": 3195000,
      "end": 3197024
    },
    {
      "path": "/texlive/texmf-dist/tex/latex/base",
      "name": "proc.cls",
      "start": 3197024,
      "end": 3201015
    },
    {
      "path": "/texlive/texmf-dist/tex/latex/base",
      "name": "proc.sty",
      "start": 3201015,
      "end": 3204822
    },
    {
      "path": "/texlive/texmf-dist/tex/latex/base",
      "name": "report.cls",
      "start": 3204822,
      "end": 3228025
    },
    {
      "path": "/texlive/texmf-dist/tex/latex/base",
      "name": "report.sty",
      "start": 3228025,
      "end": 3229759
    },
    {
      "path": "/texlive/texmf-dist/tex/latex/base",
      "name": "sample2e.tex",
      "start": 3229759,
      "end": 3236959
    },
    {
      "path": "/texlive/texmf-dist/tex/latex/base",
      "name": "sfonts.def",
      "start": 3236959,
      "end": 3238559
    },
    {
      "path": "/texlive/texmf-dist/tex/latex/base",
      "name": "shortvrb.sty",
      "start": 3238559,
      "end": 3242701
    },
    {
      "path": "/texlive/texmf-dist/tex/latex/base",
      "name": "showidx.sty",
      "start": 3242701,
      "end": 3246067
    },
    {
      "path": "/texlive/texmf-dist/tex/latex/base",
      "name": "size10.clo",
      "start": 3246067,
      "end": 3254515
    },
    {
      "path": "/texlive/texmf-dist/tex/latex/base",
      "name": "size11.clo",
      "start": 3254515,
      "end": 3262979
    },
    {
      "path": "/texlive/texmf-dist/tex/latex/base",
      "name": "size12.clo",
      "start": 3262979,
      "end": 3271428
    },
    {
      "path": "/texlive/texmf-dist/tex/latex/base",
      "name": "slides.cls",
      "start": 3271428,
      "end": 3288156
    },
    {
      "path": "/texlive/texmf-dist/tex/latex/base",
      "name": "slides.def",
      "start": 3288156,
      "end": 3306394
    },
    {
      "path": "/texlive/texmf-dist/tex/latex/base",
      "name": "slides.sty",
      "start": 3306394,
      "end": 3308128
    },
    {
      "path": "/texlive/texmf-dist/tex/latex/base",
      "name": "small2e.tex",
      "start": 3308128,
      "end": 3309822
    },
    {
      "path": "/texlive/texmf-dist/tex/latex/base",
      "name": "source2edoc.cls",
      "start": 3309822,
      "end": 3316733
    },
    {
      "path": "/texlive/texmf-dist/tex/latex/base",
      "name": "structuredlog.sty",
      "start": 3316733,
      "end": 3319519
    },
    {
      "path": "/texlive/texmf-dist/tex/latex/base",
      "name": "syntonly.sty",
      "start": 3319519,
      "end": 3322360
    },
    {
      "path": "/texlive/texmf-dist/tex/latex/base",
      "name": "t1cmdh.fd",
      "start": 3322360,
      "end": 3324530
    },
    {
      "path": "/texlive/texmf-dist/tex/latex/base",
      "name": "t1cmfib.fd",
      "start": 3324530,
      "end": 3326741
    },
    {
      "path": "/texlive/texmf-dist/tex/latex/base",
      "name": "t1cmfr.fd",
      "start": 3326741,
      "end": 3328945
    },
    {
      "path": "/texlive/texmf-dist/tex/latex/base",
      "name": "t1cmr.fd",
      "start": 3328945,
      "end": 3331514
    },
    {
      "path": "/texlive/texmf-dist/tex/latex/base",
      "name": "t1cmss.fd",
      "start": 3331514,
      "end": 3334155
    },
    {
      "path": "/texlive/texmf-dist/tex/latex/base",
      "name": "t1cmtt.fd",
      "start": 3334155,
      "end": 3336598
    },
    {
      "path": "/texlive/texmf-dist/tex/latex/base",
      "name": "t1cmvtt.fd",
      "start": 3336598,
      "end": 3338827
    },
    {
      "path": "/texlive/texmf-dist/tex/latex/base",
      "name": "t1enc.def",
      "start": 3338827,
      "end": 3349753
    },
    {
      "path": "/texlive/texmf-dist/tex/latex/base",
      "name": "t1enc.dfu",
      "start": 3349753,
      "end": 3362539
    },
    {
      "path": "/texlive/texmf-dist/tex/latex/base",
      "name": "t1enc.sty",
      "start": 3362539,
      "end": 3364336
    },
    {
      "path": "/texlive/texmf-dist/tex/latex/base",
      "name": "t1lcmss.fd",
      "start": 3364336,
      "end": 3367549
    },
    {
      "path": "/texlive/texmf-dist/tex/latex/base",
      "name": "t1lcmtt.fd",
      "start": 3367549,
      "end": 3369910
    },
    {
      "path": "/texlive/texmf-dist/tex/latex/base",
      "name": "t2aenc.dfu",
      "start": 3369910,
      "end": 3379875
    },
    {
      "path": "/texlive/texmf-dist/tex/latex/base",
      "name": "t2benc.dfu",
      "start": 3379875,
      "end": 3389610
    },
    {
      "path": "/texlive/texmf-dist/tex/latex/base",
      "name": "t2cenc.dfu",
      "start": 3389610,
      "end": 3399205
    },
    {
      "path": "/texlive/texmf-dist/tex/latex/base",
      "name": "testpage.tex",
      "start": 3399205,
      "end": 3411725
    },
    {
      "path": "/texlive/texmf-dist/tex/latex/base",
      "name": "texsys.cfg",
      "start": 3411725,
      "end": 3419792
    },
    {
      "path": "/texlive/texmf-dist/tex/latex/base",
      "name": "textcomp-2018-08-11.sty",
      "start": 3419792,
      "end": 3435904
    },
    {
      "path": "/texlive/texmf-dist/tex/latex/base",
      "name": "textcomp.sty",
      "start": 3435904,
      "end": 3438750
    },
    {
      "path": "/texlive/texmf-dist/tex/latex/base",
      "name": "tracefnt.sty",
      "start": 3438750,
      "end": 3448602
    },
    {
      "path": "/texlive/texmf-dist/tex/latex/base",
      "name": "ts1cmr.fd",
      "start": 3448602,
      "end": 3451068
    },
    {
      "path": "/texlive/texmf-dist/tex/latex/base",
      "name": "ts1cmss.fd",
      "start": 3451068,
      "end": 3453479
    },
    {
      "path": "/texlive/texmf-dist/tex/latex/base",
      "name": "ts1cmtt.fd",
      "start": 3453479,
      "end": 3455803
    },
    {
      "path": "/texlive/texmf-dist/tex/latex/base",
      "name": "ts1cmvtt.fd",
      "start": 3455803,
      "end": 3458077
    },
    {
      "path": "/texlive/texmf-dist/tex/latex/base",
      "name": "ts1enc.def",
      "start": 3458077,
      "end": 3466167
    },
    {
      "path": "/texlive/texmf-dist/tex/latex/base",
      "name": "ts1enc.dfu",
      "start": 3466167,
      "end": 3471300
    },
    {
      "path": "/texlive/texmf-dist/tex/latex/base",
      "name": "tuenc.def",
      "start": 3471300,
      "end": 3497745
    },
    {
      "path": "/texlive/texmf-dist/tex/latex/base",
      "name": "tulmdh.fd",
      "start": 3497745,
      "end": 3500019
    },
    {
      "path": "/texlive/texmf-dist/tex/latex/base",
      "name": "tulmr.fd",
      "start": 3500019,
      "end": 3504841
    },
    {
      "path": "/texlive/texmf-dist/tex/latex/base",
      "name": "tulmss.fd",
      "start": 3504841,
      "end": 3508504
    },
    {
      "path": "/texlive/texmf-dist/tex/latex/base",
      "name": "tulmssq.fd",
      "start": 3508504,
      "end": 3511248
    },
    {
      "path": "/texlive/texmf-dist/tex/latex/base",
      "name": "tulmtt.fd",
      "start": 3511248,
      "end": 3515822
    },
    {
      "path": "/texlive/texmf-dist/tex/latex/base",
      "name": "tulmvtt.fd",
      "start": 3515822,
      "end": 3519212
    },
    {
      "path": "/texlive/texmf-dist/tex/latex/base",
      "name": "ucmr.fd",
      "start": 3519212,
      "end": 3522892
    },
    {
      "path": "/texlive/texmf-dist/tex/latex/base",
      "name": "ucmss.fd",
      "start": 3522892,
      "end": 3526026
    },
    {
      "path": "/texlive/texmf-dist/tex/latex/base",
      "name": "ucmtt.fd",
      "start": 3526026,
      "end": 3528903
    },
    {
      "path": "/texlive/texmf-dist/tex/latex/base",
      "name": "ulasy.fd",
      "start": 3528903,
      "end": 3531136
    },
    {
      "path": "/texlive/texmf-dist/tex/latex/base",
      "name": "ullasy.fd",
      "start": 3531136,
      "end": 3533325
    },
    {
      "path": "/texlive/texmf-dist/tex/latex/base",
      "name": "utf8-2018.def",
      "start": 3533325,
      "end": 3543241
    },
    {
      "path": "/texlive/texmf-dist/tex/latex/base",
      "name": "utf8.def",
      "start": 3543241,
      "end": 3554747
    },
    {
      "path": "/texlive/texmf-dist/tex/latex/base",
      "name": "utf8enc.dfu",
      "start": 3554747,
      "end": 3579905
    },
    {
      "path": "/texlive/texmf-dist/tex/latex/base",
      "name": "x2enc.dfu",
      "start": 3579905,
      "end": 3591117
    },
    {
      "path": "/texlive/texmf-dist/tex/latex/tools",
      "name": ".tex",
      "start": 3591117,
      "end": 3592543
    },
    {
      "path": "/texlive/texmf-dist/tex/latex/tools",
      "name": "afterpage.sty",
      "start": 3592543,
      "end": 3596628
    },
    {
      "path": "/texlive/texmf-dist/tex/latex/tools",
      "name": "array-2016-10-06.sty",
      "start": 3596628,
      "end": 3608477
    },
    {
      "path": "/texlive/texmf-dist/tex/latex/tools",
      "name": "array-2020-02-10.sty",
      "start": 3608477,
      "end": 3621012
    },
    {
      "path": "/texlive/texmf-dist/tex/latex/tools",
      "name": "array.sty",
      "start": 3621012,
      "end": 3635564
    },
    {
      "path": "/texlive/texmf-dist/tex/latex/tools",
      "name": "bm.sty",
      "start": 3635564,
      "end": 3648800
    },
    {
      "path": "/texlive/texmf-dist/tex/latex/tools",
      "name": "calc.sty",
      "start": 3648800,
      "end": 3659014
    },
    {
      "path": "/texlive/texmf-dist/tex/latex/tools",
      "name": "dcolumn.sty",
      "start": 3659014,
      "end": 3661772
    },
    {
      "path": "/texlive/texmf-dist/tex/latex/tools",
      "name": "delarray.sty",
      "start": 3661772,
      "end": 3663929
    },
    {
      "path": "/texlive/texmf-dist/tex/latex/tools",
      "name": "e.tex",
      "start": 3663929,
      "end": 3665346
    },
    {
      "path": "/texlive/texmf-dist/tex/latex/tools",
      "name": "enumerate.sty",
      "start": 3665346,
      "end": 3668814
    },
    {
      "path": "/texlive/texmf-dist/tex/latex/tools",
      "name": "fontsmpl.sty",
      "start": 3668814,
      "end": 3675160
    },
    {
      "path": "/texlive/texmf-dist/tex/latex/tools",
      "name": "fontsmpl.tex",
      "start": 3675160,
      "end": 3677646
    },
    {
      "path": "/texlive/texmf-dist/tex/latex/tools",
      "name": "ftnright.sty",
      "start": 3677646,
      "end": 3683790
    },
    {
      "path": "/texlive/texmf-dist/tex/latex/tools",
      "name": "h.tex",
      "start": 3683790,
      "end": 3685400
    },
    {
      "path": "/texlive/texmf-dist/tex/latex/tools",
      "name": "hhline.sty",
      "start": 3685400,
      "end": 3689231
    },
    {
      "path": "/texlive/texmf-dist/tex/latex/tools",
      "name": "indentfirst.sty",
      "start": 3689231,
      "end": 3690849
    },
    {
      "path": "/texlive/texmf-dist/tex/latex/tools",
      "name": "layout.sty",
      "start": 3690849,
      "end": 3705756
    },
    {
      "path": "/texlive/texmf-dist/tex/latex/tools",
      "name": "longtable-2020-01-07.sty",
      "start": 3705756,
      "end": 3718038
    },
    {
      "path": "/texlive/texmf-dist/tex/latex/tools",
      "name": "longtable.sty",
      "start": 3718038,
      "end": 3733938
    },
    {
      "path": "/texlive/texmf-dist/tex/latex/tools",
      "name": "multicol-2017-04-11.sty",
      "start": 3733938,
      "end": 3763750
    },
    {
      "path": "/texlive/texmf-dist/tex/latex/tools",
      "name": "multicol-2019-10-01.sty",
      "start": 3763750,
      "end": 3795217
    },
    {
      "path": "/texlive/texmf-dist/tex/latex/tools",
      "name": "multicol.sty",
      "start": 3795217,
      "end": 3828096
    },
    {
      "path": "/texlive/texmf-dist/tex/latex/tools",
      "name": "q.tex",
      "start": 3828096,
      "end": 3829507
    },
    {
      "path": "/texlive/texmf-dist/tex/latex/tools",
      "name": "r.tex",
      "start": 3829507,
      "end": 3830920
    },
    {
      "path": "/texlive/texmf-dist/tex/latex/tools",
      "name": "rawfonts.sty",
      "start": 3830920,
      "end": 3837655
    },
    {
      "path": "/texlive/texmf-dist/tex/latex/tools",
      "name": "s.tex",
      "start": 3837655,
      "end": 3839067
    },
    {
      "path": "/texlive/texmf-dist/tex/latex/tools",
      "name": "shellesc.sty",
      "start": 3839067,
      "end": 3843188
    },
    {
      "path": "/texlive/texmf-dist/tex/latex/tools",
      "name": "showkeys-2014-10-28.sty",
      "start": 3843188,
      "end": 3851968
    },
    {
      "path": "/texlive/texmf-dist/tex/latex/tools",
      "name": "showkeys.sty",
      "start": 3851968,
      "end": 3860760
    },
    {
      "path": "/texlive/texmf-dist/tex/latex/tools",
      "name": "somedefs.sty",
      "start": 3860760,
      "end": 3863245
    },
    {
      "path": "/texlive/texmf-dist/tex/latex/tools",
      "name": "tabularx.sty",
      "start": 3863245,
      "end": 3870488
    },
    {
      "path": "/texlive/texmf-dist/tex/latex/tools",
      "name": "thb.sty",
      "start": 3870488,
      "end": 3872527
    },
    {
      "path": "/texlive/texmf-dist/tex/latex/tools",
      "name": "thc.sty",
      "start": 3872527,
      "end": 3874433
    },
    {
      "path": "/texlive/texmf-dist/tex/latex/tools",
      "name": "thcb.sty",
      "start": 3874433,
      "end": 3876481
    },
    {
      "path": "/texlive/texmf-dist/tex/latex/tools",
      "name": "theorem.sty",
      "start": 3876481,
      "end": 3881437
    },
    {
      "path": "/texlive/texmf-dist/tex/latex/tools",
      "name": "thm.sty",
      "start": 3881437,
      "end": 3883353
    },
    {
      "path": "/texlive/texmf-dist/tex/latex/tools",
      "name": "thmb.sty",
      "start": 3883353,
      "end": 3885430
    },
    {
      "path": "/texlive/texmf-dist/tex/latex/tools",
      "name": "thp.sty",
      "start": 3885430,
      "end": 3887338
    },
    {
      "path": "/texlive/texmf-dist/tex/latex/tools",
      "name": "trace.sty",
      "start": 3887338,
      "end": 3891639
    },
    {
      "path": "/texlive/texmf-dist/tex/latex/tools",
      "name": "varioref-2016-02-16.sty",
      "start": 3891639,
      "end": 3925650
    },
    {
      "path": "/texlive/texmf-dist/tex/latex/tools",
      "name": "varioref.sty",
      "start": 3925650,
      "end": 3969698
    },
    {
      "path": "/texlive/texmf-dist/tex/latex/tools",
      "name": "verbatim.sty",
      "start": 3969698,
      "end": 3977230
    },
    {
      "path": "/texlive/texmf-dist/tex/latex/tools",
      "name": "verbtest.tex",
      "start": 3977230,
      "end": 3982510
    },
    {
      "path": "/texlive/texmf-dist/tex/latex/tools",
      "name": "x.tex",
      "start": 3982510,
      "end": 3983927
    },
    {
      "path": "/texlive/texmf-dist/tex/latex/tools",
      "name": "xr.sty",
      "start": 3983927,
      "end": 3987577
    },
    {
      "path": "/texlive/texmf-dist/tex/latex/tools",
      "name": "xspace.sty",
      "start": 3987577,
      "end": 3992122
    },
    {
      "path": "/texlive/texmf-dist/texmf-config",
      "name": "ls-R",
      "start": 3992122,
      "end": 3992203
    },
    {
      "path": "/texlive/texmf-dist/texmf-var",
      "name": "ls-R",
      "start": 3992203,
      "end": 3993220
    },
    {
      "path": "/texlive/texmf-dist/web2c",
      "name": "amiga-pl.tcx",
      "start": 3993220,
      "end": 3998540
    },
    {
      "path": "/texlive/texmf-dist/web2c",
      "name": "cp1250cs.tcx",
      "start": 3998540,
      "end": 3999564
    },
    {
      "path": "/texlive/texmf-dist/web2c",
      "name": "cp1250pl.tcx",
      "start": 3999564,
      "end": 4005137
    },
    {
      "path": "/texlive/texmf-dist/web2c",
      "name": "cp1250t1.tcx",
      "start": 4005137,
      "end": 4010210
    },
    {
      "path": "/texlive/texmf-dist/web2c",
      "name": "cp227.tcx",
      "start": 4010210,
      "end": 4013710
    },
    {
      "path": "/texlive/texmf-dist/web2c",
      "name": "cp852-cs.tcx",
      "start": 4013710,
      "end": 4014695
    },
    {
      "path": "/texlive/texmf-dist/web2c",
      "name": "cp852-pl.tcx",
      "start": 4014695,
      "end": 4020461
    },
    {
      "path": "/texlive/texmf-dist/web2c",
      "name": "cp8bit.tcx",
      "start": 4020461,
      "end": 4023459
    },
    {
      "path": "/texlive/texmf-dist/web2c",
      "name": "empty.tcx",
      "start": 4023459,
      "end": 4024062
    },
    {
      "path": "/texlive/texmf-dist/web2c",
      "name": "fmtutil-hdr.cnf",
      "start": 4024062,
      "end": 4025828
    },
    {
      "path": "/texlive/texmf-dist/web2c",
      "name": "fmtutil.cnf",
      "start": 4025828,
      "end": 4028750
    },
    {
      "path": "/texlive/texmf-dist/web2c",
      "name": "il1-t1.tcx",
      "start": 4028750,
      "end": 4034111
    },
    {
      "path": "/texlive/texmf-dist/web2c",
      "name": "il2-cs.tcx",
      "start": 4034111,
      "end": 4035097
    },
    {
      "path": "/texlive/texmf-dist/web2c",
      "name": "il2-pl.tcx",
      "start": 4035097,
      "end": 4040669
    },
    {
      "path": "/texlive/texmf-dist/web2c",
      "name": "il2-t1.tcx",
      "start": 4040669,
      "end": 4045784
    },
    {
      "path": "/texlive/texmf-dist/web2c",
      "name": "kam-cs.tcx",
      "start": 4045784,
      "end": 4046704
    },
    {
      "path": "/texlive/texmf-dist/web2c",
      "name": "kam-t1.tcx",
      "start": 4046704,
      "end": 4047599
    },
    {
      "path": "/texlive/texmf-dist/web2c",
      "name": "macce-pl.tcx",
      "start": 4047599,
      "end": 4053508
    },
    {
      "path": "/texlive/texmf-dist/web2c",
      "name": "macce-t1.tcx",
      "start": 4053508,
      "end": 4059281
    },
    {
      "path": "/texlive/texmf-dist/web2c",
      "name": "maz-pl.tcx",
      "start": 4059281,
      "end": 4065294
    },
    {
      "path": "/texlive/texmf-dist/web2c",
      "name": "mktex.cnf",
      "start": 4065294,
      "end": 4065365
    },
    {
      "path": "/texlive/texmf-dist/web2c",
      "name": "mktex.opt",
      "start": 4065365,
      "end": 4070155
    },
    {
      "path": "/texlive/texmf-dist/web2c",
      "name": "mktexdir.opt",
      "start": 4070155,
      "end": 4070474
    },
    {
      "path": "/texlive/texmf-dist/web2c",
      "name": "mktexnam.opt",
      "start": 4070474,
      "end": 4074312
    },
    {
      "path": "/texlive/texmf-dist/web2c",
      "name": "natural.tcx",
      "start": 4074312,
      "end": 4076618
    },
    {
      "path": "/texlive/texmf-dist/web2c",
      "name": "tcvn-t5.tcx",
      "start": 4076618,
      "end": 4080012
    },
    {
      "path": "/texlive/texmf-dist/web2c",
      "name": "texmf.cnf",
      "start": 4080012,
      "end": 4120757
    },
    {
      "path": "/texlive/texmf-dist/web2c",
      "name": "texmfcnf.lua",
      "start": 4120757,
      "end": 4133546
    },
    {
      "path": "/texlive/texmf-dist/web2c",
      "name": "updmap-hdr.cfg",
      "start": 4133546,
      "end": 4137057
    },
    {
      "path": "/texlive/texmf-dist/web2c",
      "name": "updmap.cfg",
      "start": 4137057,
      "end": 4140944
    },
    {
      "path": "/texlive/texmf-dist/web2c",
      "name": "viscii-t5.tcx",
      "start": 4140944,
      "end": 4144343
    }
  ],
  "totalSize": 4144343
}